hyperify_rune/__init__.py
hyperify_rune/__main__.py
hyperify_rune-0.1.6.dist-info/METADATA
hyperify_rune-0.1.6.dist-info/WHEEL
hyperify_rune-0.1.6.dist-info/entry_points.txt
hyperify_rune-0.1.6.dist-info/licenses/LICENSE.md
hyperify_rune-0.1.6.dist-info/RECORD
