Metadata-Version: 2.4
Name: hyperify-rune
Version: 0.1.6
Summary: A Python package for Hyperify Rune
Project-URL: Homepage, https://github.com/hyperifyio/rune
Project-URL: Bug Tracker, https://github.com/hyperifyio/rune/issues
Author-email: Hyperify <info@hyperify.io>
License-File: LICENSE.md
Classifier: License :: OSI Approved :: MIT License
Classifier: Operating System :: OS Independent
Classifier: Programming Language :: Python :: 3
Requires-Python: >=3.7
Requires-Dist: beautifulsoup4>=4.11.0
Requires-Dist: esprima>=4.0.1
Requires-Dist: lxml>=5.3.0
Requires-Dist: mistune>=3.1.0
Requires-Dist: pyyaml>=6.0
